{"stats":{"minecraft:picked_up":{"minecraft:brown_mushroom":1,"minecraft:red_mushroom":1,"minecraft:mangrove_propagule":1},"minecraft:used":{"minecraft:breeze_spawn_egg":1},"minecraft:custom":{"minecraft:jump":8,"minecraft:time_since_rest":2791,"minecraft:crouch_one_cm":98,"minecraft:leave_game":1,"minecraft:sprint_one_cm":553,"minecraft:play_time":2791,"minecraft:time_since_death":2791,"minecraft:walk_one_cm":1674,"minecraft:sneak_time":167,"minecraft:total_world_time":2825,"minecraft:fly_one_cm":13678}},"DataVersion":3465}